README
setup.py
amalgam/__init__.py
amalgam/metabase.py
amalgam/utils.py
amalgam.egg-info/PKG-INFO
amalgam.egg-info/SOURCES.txt
amalgam.egg-info/dependency_links.txt
amalgam.egg-info/requires.txt
amalgam.egg-info/top_level.txt
amalgam/backends/__init__.py
amalgam/backends/base/__init__.py
amalgam/backends/base/backend.py
amalgam/backends/base/columns.py
amalgam/backends/sqla/__init__.py
amalgam/backends/sqla/backend.py
amalgam/backends/sqla/base.py
amalgam/backends/sqla/columns.py
amalgam/backends/sqla/meta.py
amalgam/backends/sqla/process.py
tests/__init__.py
tests/base_test.py
tests/m2m_test.py