Metadata-Version: 1.0
Name: amalgam
Version: 0.4.3
Summary: Minimal wrapper for database access
Home-page: http://hg.piranha.org.ua/amalgam/
Author: Alexander Solovyov
Author-email: alexander@solovyov.net
License: BSD
Platform: UNKNOWN
Classifier: Intended Audience :: Developers
Classifier: License :: OSI Approved :: BSD License
Classifier: Operating System :: OS Independent
Classifier: Programming Language :: Python
Classifier: Topic :: Database :: Front-Ends
